claude_to_sqlite/__init__.py
claude_to_sqlite/__main__.py
claude_to_sqlite/cli.py
claude_to_sqlite-0.2.dist-info/LICENSE
claude_to_sqlite-0.2.dist-info/METADATA
claude_to_sqlite-0.2.dist-info/WHEEL
claude_to_sqlite-0.2.dist-info/entry_points.txt
claude_to_sqlite-0.2.dist-info/top_level.txt
claude_to_sqlite-0.2.dist-info/RECORD
