Metadata-Version: 2.1
Name: claude-to-sqlite
Version: 0.2
Summary: Convert a Claude.ai export to SQLite
Author: Simon Willison
License: Apache-2.0
Project-URL: Homepage, https://github.com/simonw/claude-to-sqlite
Project-URL: Changelog, https://github.com/simonw/claude-to-sqlite/releases
Project-URL: Issues, https://github.com/simonw/claude-to-sqlite/issues
Project-URL: CI, https://github.com/simonw/claude-to-sqlite/actions
Classifier: License :: OSI Approved :: Apache Software License
Requires-Python: >=3.8
License-File: LICENSE
Requires-Dist: click
Requires-Dist: sqlite-utils
Requires-Dist: cogapp
Provides-Extra: test
Requires-Dist: pytest ; extra == 'test'
